pybmtool/__init__.py
pybmtool/__main__.py
pybmtool/bmtool.py
pybmtool/parser.py
pybmtool/utils.py
pybmtool-0.1.4.dist-info/entry_points.txt
pybmtool-0.1.4.dist-info/LICENSE
pybmtool-0.1.4.dist-info/WHEEL
pybmtool-0.1.4.dist-info/METADATA
pybmtool-0.1.4.dist-info/RECORD
