Metadata-Version: 2.1
Name: pybmtool
Version: 0.1.4
Summary: A Python library/CLI tool for parsing Apple's BuildManifest plist files inside a firmware ipsw/ota.
Home-page: https://github.com/Cryptiiiic/BMTool
License: LGPL-3.0-only
Author: Cryptiiiic
Author-email: liamwqs@gmail.com
Requires-Python: >=3.10,<4.0
Classifier: License :: OSI Approved :: GNU Lesser General Public License v3 (LGPLv3)
Classifier: Programming Language :: Python :: 3
Classifier: Programming Language :: Python :: 3.10
Requires-Dist: click (>=8.1.3,<9.0.0)
Requires-Dist: remotezip (>=0.9.4,<0.10.0)
Project-URL: Bug Tracker, https://github.com/Cryptiiiic/BMTool/issues
Project-URL: Repository, https://github.com/Cryptiiiic/BMTool
